pillowlatex/__init__.py
pillowlatex/latex.py
pillowlatex/latexenvfuncs.py
pillowlatex/latexfuncs.py
pillowlatex/settings.py
pillowlatex/fonts/STIXTwoMath-Regular.ttf
pillowlatex-0.1.4.dist-info/licenses/LICENSE
pillowlatex-0.1.4.dist-info/METADATA
pillowlatex-0.1.4.dist-info/WHEEL
pillowlatex-0.1.4.dist-info/top_level.txt
pillowlatex-0.1.4.dist-info/RECORD
