Metadata-Version: 2.4
Name: pillowlatex
Version: 0.1.4
Summary: 基于 Pillow 的简易 LaTeX 渲染库，用于快速渲染大模型返回的 LaTeX 公式为图片。
Author-email: 迷梦龙 <614675349@qq.com>
License-Expression: MIT
Project-URL: homepage, https://github.com/Monody-S/pillowlatex
Keywords: latex,pillow,image,rendering
Classifier: Development Status :: 5 - Production/Stable
Classifier: Intended Audience :: Developers
Classifier: Natural Language :: Chinese (Simplified)
Classifier: Programming Language :: Python :: 3
Classifier: Programming Language :: Python :: 3.9
Classifier: Programming Language :: Python :: 3.10
Classifier: Programming Language :: Python :: 3.11
Classifier: Programming Language :: Python :: 3.12
Classifier: Programming Language :: Python :: 3.13
Classifier: Operating System :: OS Independent
Classifier: Topic :: Software Development :: Libraries :: Python Modules
Requires-Python: <4.0,>=3.9
License-File: LICENSE
Requires-Dist: pillow
Requires-Dist: fonttools
Dynamic: license-file
